calculator_basic/__init__.py
calculator_basic-0.1.dist-info/LICENSE.txt
calculator_basic-0.1.dist-info/METADATA
calculator_basic-0.1.dist-info/WHEEL
calculator_basic-0.1.dist-info/top_level.txt
calculator_basic-0.1.dist-info/RECORD
