Metadata-Version: 2.1
Name: calculator-basic
Version: 0.1
Summary: This is very basic calculator
Author: Jenis Donda
Author-email: jenis.donda@crestdatasys.com
Classifier: Programming Language :: Python :: 3
Classifier: License :: OSI Approved :: MIT License
Classifier: Operating System :: OS Independent
License-File: LICENSE.txt
